[
    {
        "username": "ashwin@gmail.com",
        "password": "ashwin",
        "userType": "patient",
        "verifiedUser": true,
        "premiumUser": true,
        "email": "ashwin@gmail.com",
        "phone": "9356127116",
        "location": "pollachi",
        "age": "22",
        "name": "ashwin gopalsamy"
    },
    {
        "username": "yalini@gmail.com",
        "password": "yalini",
        "userType": "doctor",
        "verifiedUser": true,
        "premiumUser": true,
        "email": "yalini@gmail.com",
        "name": "keerthana yalini",
        "phone": "9356127117",
        "location": "pollachi",
        "age": "22"
    },
    {
        "username": "gopalsamy@gmail.com",
        "password": "gopal",
        "userType": "doctor",
        "verifiedUser": true,
        "premiumUser": true,
        "email": "gopalsamy@gmail.com",
        "name": "p gopalsamy",
        "phone": "9356127118",
        "location": "pollachi",
        "age": "63"
    },
    {
        "username": "malathigopalsamy@gmail.com",
        "password": "gopal",
        "userType": "patient",
        "verifiedUser": true,
        "premiumUser": true,
        "email": "malathigopalsamy@gmail.com",
        "name": "malathi gopalsamy",
        "phone": "9356127119",
        "location": "pollachi",
        "age": "52"
    },
    {
        "username": "rajavinith@gmail.com",
        "password": "vinith",
        "userType": "doctor",
        "verifiedUser": true,
        "premiumUser": true,
        "email": "rajavinith@gmail.com",
        "name": "raja vinith",
        "phone": "9356127120",
        "location": "pollachi",
        "age": "22"
    }, {
        "username": "masteradmin@medo.com",
        "password": "masteradmin",
        "userType": "masteradmin",
        "verifiedUser": true,
        "premiumUser": true,
        "email": "masteradmin@medo.com",
        "phone": "1234567890",
        "location": "pollachi",
        "age": "44"
    },
    {
        "username": "admin@medo.com",
        "password": "admin",
        "userType": "admin",
        "verifiedUser": true,
        "premiumUser": true,
        "email": "admin@medo.com",
        "phone": "1234567890",
        "location": "pollachi",
        "age": "44"
    }
]